{
  "date": "2026. 7. 8.",
  "sessions": [
    {
      "time": "오전 07:50",
      "episode": "The Office - S01E05  Basketball",
      "dialogues": [
        "Loser buys dinner at Farley's.",
        "But, you know, it's really just, uh, a good friendly game.",
        "This is the smallest amount of power",
        "The last time I was down there, I noticed",
        "My fiance has plans for us this Saturday,",
        "You're, uh, you're chickenin' out.",
        "Yeah. Because corporate, uh,",
        "Her toaster oven broke.",
        "And I think that that should be...",
        "So! Um, 1:00 sharp and we've got a game on."
      ],
      "koreanHints": [
        "1. 진 사람이 팔리스에서 저녁 사는 거다.",
        "2. 넌 꼬리 내리는 거지.",
        "3. 그냥 친선 경기일 뿐이야."
      ],
      "keyExpressions": "💡 핵심 표현:\n- Loser buys : 내기에서 진 사람이 비용을 부담한다는 뜻. 친구들끼리 가볍게 내기할 때 흔히 쓰는 표현\n- chicken out : 겁먹고 포기하다, 꼬리 내리다. chickenin' out처럼 구어체로 g를 생략해서 발음하기도 함\n- friendly game : 승부에 연연하지 않는 가벼운 친선 경기. 경쟁보다 즐거움이 목적임을 강조할 때 사용"
    }
  ]
}