{
  "date": "2026. 4. 30.",
  "sessions": [
    {
      "time": "AM 07:45",
      "episode": "Modern Family - S09E14  Written in the Stars",
      "dialogues": [
        "Sor... Sorry, I'm a little obsessed with space.",
        "to find a good-looking genius?",
        "I have never had that drink.",
        "Can we have a... Can we have a different table?",
        "No, I mean, um... Thank you.",
        "How can you not hear this?",
        "Well, I'm sorry, Joe. I don't owe you anything.",
        "(voice breaking) Oh, my God, Mitchell.",
        "Oh, my G... No. What?",
        "(hushed) We've really only texted."
      ],
      "koreanHints": [
        "1. 미안, 나 우주에 좀 과하게 빠져있어.",
        "2. 다른 테이블로 옮겨도 될까요?",
        "3. 이거 안 들려? 어떻게 못 들어?"
      ],
      "keyExpressions": "💡 핵심 표현:\n- I'm obsessed with : 단순히 '좋아한다'를 넘어서 집착 수준으로 빠져있다는 의미. I like나 I love보다 훨씬 강한 표현으로 원어민들이 일상에서 자주 사용\n- Can we have a different : 레스토랑이나 서비스 상황에서 무언가를 바꿔달라고 정중하게 요청할 때 쓰는 표현. Can I get 보다 Can we have가 더 공손한 뉘앙스\n- How can you not : '어떻게 ~하지 않을 수 있어?'라는 의미로, 상대방이 당연히 해야 할 것을 하지 않을 때 놀라움이나 불만을 표현하는 수사적 질문"
    },
    {
      "time": "PM 02:32",
      "episode": "Seinfeld - S09E18  The Frogger",
      "dialogues": [
        "[FROGGER POWERING DOWN]",
        "I think it's nice. ELAINE: What?!",
        "How come I haven't read about it?",
        "do you wanna come with us to Mario's Pizza?",
        "No. I-I need a guy that can rig a Frogger machine",
        "All right, make it the large sodas.",
        "PETERMAN: ♪ Get well Get well soon ♪",
        "Be that long. I mean, most action movies are...",
        "Well, I'm doing it, Jerry.",
        "I mean, now we're celebrating a sick day?"
      ],
      "koreanHints": [
        "1. 그렇게 오래 걸리진 않을 거야. 액션 영화 대부분은...",
        "2. 글쎄, 난 할 거야, 제리.",
        "3. 이제 우리가 병가를 축하하는 거야?"
      ],
      "keyExpressions": "💡 핵심 표현:\n- Be that long : 문맥상 앞의 won't/can't 등을 생략한 구어체 표현. \"그렇게 오래 걸리지 않을 거야\"라는 뉘앙스로 원어민들이 캐주얼한 대화에서 자주 쓰는 축약형\n- I'm doing it : 단순히 \"할 거야\"가 아니라 \"반대에도 불구하고 내 의지대로 밀고 나가겠다\"는 결연한 의지를 담은 표현\n- now we're celebrating~ : \"이제 우리가 ~까지 축하하는 거야?\"라며 상황이 과하거나 이상하다고 지적할 때 쓰는 반어적 표현"
    }
  ]
}