{
  "date": "2026. 6. 21.",
  "sessions": [
    {
      "time": "오전 07:57",
      "episode": "Modern Family - S04E17  Best Men",
      "dialogues": [
        "People do it all the time.",
        "Marriage is a promise.",
        "I thought this was supposed to be some sort of classical thing. Me too.",
        "She can't get married if the best man doesn't hand over the wedding ring.",
        "and hear you play? Mmm, that's okay.",
        "Do you wanna go? So what's-What's Noodlecat?",
        "before I meet up with Zoe and those guys at Noodlecat.",
        "How long are you gonna be there? No, it's fine. It's fine. Go.",
        "but what she is doing is not marriage.",
        "If it makes you feel any better, I was never gonna do that."
      ],
      "koreanHints": [
        "1. 사람들 항상 그렇게 하잖아.",
        "2. 결혼은 약속이야.",
        "3. 기분이 좀 나아진다면, 나도 애초에 그럴 생각 없었어."
      ],
      "keyExpressions": "💡 핵심 표현:\n- all the time : 단순히 '항상'이 아니라 '흔하게, 별일 아니라는 듯이'라는 뉘앙스. 상대방을 안심시키거나 일상적임을 강조할 때 사용\n- Marriage is a promise : 추상 명사를 정의할 때 관사 없이 사용하는 격언 스타일. 무게감 있는 주장이나 가치관을 표현할 때 효과적\n- If it makes you feel any better : 위로할 때 쓰는 완곡한 표현. 상대방의 기분을 배려하며 정보를 전달하는 원어민 특유의 커뮤니케이션 방식\n- be never gonna : 'be going to'의 구어체 축약. 애초에 의도나 계획이 없었음을 강조"
    },
    {
      "time": "오후 03:53",
      "episode": "Modern Family - S02E24  The One That Got Away",
      "dialogues": [
        "Have fun. Bye, sweetie.",
        "She's really smart and funny, but she's on a softball team.",
        "Okay, but don't go far away because I might need help with the zipper, okay?",
        "Yeah, what's with that? Who are they trying to keep out anyway?",
        "and I wasn't gonna dent this one.",
        "Hey, Cam. Oh, hey, Manny.",
        "I'll never forget the looks I got driving that baby down the block,",
        "Whoa. Where did you learn how to do that?",
        "Oh, no, it's not what you think. I'm talking to a little boy.",
        "Yeah. I'm just water washing my hands!"
      ],
      "koreanHints": [
        "1. 멀리 가지는 마. 지퍼 올리는 거 도와줘야 할 수도 있으니까.",
        "2. 도대체 뭐가 문제야? 대체 누구를 막으려는 거야?",
        "3. 그걸 어디서 배웠어?"
      ],
      "keyExpressions": "💡 핵심 표현:\n- don't go far away : 멀리 가지 말라는 표현. 물리적으로 가까이 있어달라고 부탁할 때 씀\n- what's with that? : 그게 뭐야? 왜 그래? 뭔가 이상하거나 이해 안 되는 상황에 대해 물을 때 쓰는 구어체 표현\n- keep out : 들어오지 못하게 막다, 출입을 금지하다. keep someone out 형태로 특정 대상을 차단할 때 사용\n- Where did you learn how to do that? : 누군가 능숙하게 뭔가를 해냈을 때 놀라며 묻는 자연스러운 질문 패턴\n- anyway : 문장 끝에 붙여서 '대체', '도대체'의 뉘앙스를 더함. 약간 따지는 듯한 어조"
    },
    {
      "time": "오후 07:28",
      "episode": "Friends - S04E08  The One with Chandler in a Box",
      "dialogues": [
        "Remember that necklace I gave you last year?",
        "CHANDLER [OVER PHONE]: Look, I never should've kissed your girlfriend, and I'm...",
        "- Yes. - Yes. She's very excited about that.",
        "They couldn't be worse. I spent eight hours calling him...",
        "It's not about her. Okay?",
        "Well, she wore it all Christmas day and then, uh...",
        "...this year maybe we could do Secret Santa and then we each only buy one gift.",
        "- Because I wanna trade for her. - I picked her. Oh, thank God, you want her.",
        "- Her initials. - Oh.",
        "And that's why I'm leaving."
      ],
      "koreanHints": [
        "1. 그게 그녀에 관한 게 아니야, 알겠어?",
        "2. 더 나쁠 순 없었어. 8시간 동안 그한테 전화했거든...",
        "3. 올해는 시크릿 산타를 하면 어떨까, 그럼 우리 각자 선물 하나씩만 사면 되잖아."
      ],
      "keyExpressions": "💡 핵심 표현:\n- It's not about ~ : ~에 관한 문제가 아니다. 대화에서 초점을 다른 곳으로 돌릴 때 쓰는 표현\n- couldn't be worse : 최악이다, 더 나쁠 수 없다. 상황이 정말 안 좋을 때 강조하는 표현\n- spend + 시간 + -ing : ~하는 데 시간을 쓰다. 시간 소비를 강조할 때 자주 쓰임\n- do Secret Santa : 시크릿 산타를 하다. 선물 교환 방식을 제안할 때 쓰는 표현\n- we each : 우리 각자. each를 강조해서 개별성을 나타내는 패턴"
    },
    {
      "time": "오후 10:58",
      "episode": "Modern Family - S05E23  The Wedding (1)",
      "dialogues": [
        "Excuse me. Could someone help me to find the back of the line?",
        "but the best decision I ever made.",
        "Should we consider the possibility...",
        "- Uh, so, wh-where's Tony? - Oh, beats me.",
        "Come on. What has been going on with you recently?",
        "When you lose one sense, all your other senses become heightened.",
        "Yes, I did, because I wanted to spend some time with my son.",
        "You've... You've been pushing me away so much lately,",
        "No, really, be serious.",
        "Yeah, she doesn't mean that."
      ],
      "koreanHints": [
        "1. 최근에 너 도대체 무슨 일 있는 거야?",
        "2. 네가 요즘 나를 너무 밀어내고 있잖아.",
        "3. 한 감각을 잃으면, 다른 모든 감각이 더 예민해지게 돼."
      ],
      "keyExpressions": "💡 핵심 표현:\n- What has been going on with you : 상대방에게 무슨 일이 있는지, 왜 평소와 다른지 물어볼 때 쓰는 표현. What's wrong보다 더 구체적으로 최근의 변화나 상황을 묻는 뉘앙스\n- push someone away : 누군가를 감정적으로 밀어내다, 거리를 두다는 의미. 물리적이 아닌 관계에서의 거리두기를 나타냄\n- become heightened : 감각, 감정, 긴장 등이 고조되거나 예민해진다는 의미. 단순히 increase보다 더 강렬한 느낌\n- lately : recently와 비슷하지만 현재완료 시제와 자주 쓰이며 '요즘 들어' 라는 뉘앙스가 강함\n- beats me : 모르겠다는 의미의 구어체 표현. I don't know보다 캐주얼함"
    }
  ]
}