{
  "date": "2026. 5. 25.",
  "sessions": [
    {
      "time": "AM 07:46",
      "episode": "The Office - S09E09  Dwight Christmas",
      "dialogues": [
        "possibly be forgetting?",
        "so I can get a real good night",
        "for my first day of work.",
        "a mini-version of cake?",
        "have my kneecap shattered",
        "Funny how that works.",
        "philia meaning \"love,\"",
        "What about an authentic",
        "It makes your neck look",
        "Merry Christmas, everyone!"
      ],
      "koreanHints": [
        "1. 그것 참 묘하게 돌아가네요.",
        "2. 첫 출근날을 위해서요.",
        "3. 모두들 메리 크리스마스!"
      ],
      "keyExpressions": "💡 핵심 표현:\n- Funny how... : 상황의 아이러니나 우연의 일치를 지적할 때 쓰는 표현. \"그것 참 재미있게도/묘하게도\"라는 뉘앙스로, 실제로 웃긴 게 아니라 역설적이거나 흥미로운 상황을 언급할 때 사용\n- first day of work : \"첫 출근날\"을 의미하는 자연스러운 표현. \"first working day\"보다 훨씬 자연스럽고 일상적\n- everyone : 여러 사람에게 인사하거나 공지할 때 자주 쓰는 호칭. \"everybody\"보다 약간 더 격식 있는 느낌"
    },
    {
      "time": "PM 03:37",
      "episode": "How I Met Your Mother - S01E09  Belly Full of Turkey",
      "dialogues": [
        "If you miss it, I'm leaving you.",
        "I'm just, I'm a little distracted.",
        "The point is, it made us remember",
        "Atta girl. Keep it cool.",
        "Right, guys? He's gonna be a little Browns fan.",
        "He's never done that before.",
        "but I can't stand watching you make a fool of yourself.",
        "God, you said that out loud!",
        "You know what they say: a watched tot never crawls.",
        "You are such a good folder."
      ],
      "koreanHints": [
        "1. 나 지금 좀 정신이 없어서.",
        "2. 네가 바보같이 구는 걸 보고만 있을 수가 없어서.",
        "3. 지켜보고 있으면 절대 안 기는 법이야. (아기가)"
      ],
      "keyExpressions": "💡 핵심 표현:\n- I'm a little distracted : 집중이 안 되거나 다른 생각으로 정신이 없을 때 쓰는 표현. \"정신이 산만하다\"보다 부드럽고 자연스러운 뉘앙스\n- can't stand -ing : \"~하는 것을 참을 수 없다, 견딜 수 없다\"는 의미로 hate보다 더 강한 거부감을 표현\n- make a fool of yourself : 자신을 우스꽝스럽게 만들다, 망신을 당하다는 의미의 관용구\n- You know what they say : \"사람들이 말하잖아, 흔히 말하듯이\"라는 의미로 속담이나 격언을 인용할 때 앞에 붙이는 표현\n- A watched pot never boils : 원래 속담을 변형한 표현. 기다리면서 지켜보면 더 안 되는 것 같다는 뉘앙스"
    },
    {
      "time": "PM 08:09",
      "episode": "Friends - S03E11  The One Where Chandler Can't Remember Which Sister",
      "dialogues": [
        "OH, YEAH? WHAT'S IT ABOUT?",
        "I SAW THAT GIRL KATHERINE AFTER WE BROKE UP.",
        "UH, YOU KNOW, THIS, UH, BUILDING'S ON MY PAPER ROUTE, SO, UH...",
        "OH, LOOK, WHEN I'VE BEEN DRINKING",
        "YOU KNOW, IF IT'S ANY CONSOLATION",
        "BY GROPING MY SISTER?",
        "YOU DON'T HAVE TO THROW A PARTY FOR ME.",
        "'CAUSE HE THOUGHT I WAS MARY ANGELA.",
        "OH, THAT SOUNDS GREAT.",
        "( muffled moaning and groaning)"
      ],
      "koreanHints": [
        "1. 그게 무슨 위로가 될지 모르겠지만",
        "2. 내가 술 마시면 말이야",
        "3. 그거 좋은데요."
      ],
      "keyExpressions": "💡 핵심 표현:\n- if it's any consolation : 위로가 될지 모르겠지만, 도움이 될지 모르겠지만이라는 뜻으로 나쁜 소식이나 상황을 전할 때 부드럽게 만들어주는 표현\n- when I've been drinking : 술을 마셨을 때, 취했을 때라는 뜻으로 현재완료 진행형을 써서 술의 영향이 지속되는 상태를 자연스럽게 표현\n- that sounds great : 그거 좋다, 좋은데라는 뜻으로 제안이나 아이디어에 긍정적으로 반응할 때 가장 흔하게 쓰는 표현"
    }
  ]
}